markdown_merge/__init__.py
markdown_merge/_modidx.py
markdown_merge/core.py
markdown_merge-0.1.7.dist-info/licenses/LICENSE
markdown_merge-0.1.7.dist-info/METADATA
markdown_merge-0.1.7.dist-info/WHEEL
markdown_merge-0.1.7.dist-info/entry_points.txt
markdown_merge-0.1.7.dist-info/top_level.txt
markdown_merge-0.1.7.dist-info/RECORD
